hfdownloader/__init__.py
hfdownloader/hf_downloader.py
hfdownloader-1.0.2.dist-info/LICENSE
hfdownloader-1.0.2.dist-info/METADATA
hfdownloader-1.0.2.dist-info/WHEEL
hfdownloader-1.0.2.dist-info/top_level.txt
hfdownloader-1.0.2.dist-info/RECORD
