Metadata-Version: 2.1
Name: hfdownloader
Version: 1.0.2
Summary: A package that downloads a model from the HuggingFace Model Hub.
Home-page: https://github.com/Solonce/HFDownloader
Author: Solomon Ince
Author-email: sollyince@gmail.com
Project-URL: Bug Tracker, https://github.com/Solonce/HFDownloader/issues
Classifier: Programming Language :: Python :: 3
Classifier: License :: OSI Approved :: MIT License
Classifier: Operating System :: OS Independent
Requires-Python: >=3.6
License-File: LICENSE
